GuardianLayer/LoopDetector.py
GuardianLayer/__init__.py
GuardianLayer/advice_generator.py
GuardianLayer/cache.py
GuardianLayer/config.py
GuardianLayer/experience_layer.py
GuardianLayer/guardian.py
GuardianLayer/health_monitor.py
GuardianLayer/interfaces.py
GuardianLayer/logging_config.py
GuardianLayer/mcp_facade.py
GuardianLayer/metrics.py
GuardianLayer/providers.py
GuardianLayer/py.typed
guardianlayer-2.0.5.dist-info/licenses/LICENSE
guardianlayer-2.0.5.dist-info/METADATA
guardianlayer-2.0.5.dist-info/WHEEL
guardianlayer-2.0.5.dist-info/top_level.txt
guardianlayer-2.0.5.dist-info/RECORD
