Metadata-Version: 2.4
Name: GuardianLayer
Version: 2.0.5
Summary: Meta-cognition layer for AI agents - prevents infinite loops, learns from failures, provides self-awareness
Author-email: Michael <xvorpxvobby@gmail.com>
Maintainer-email: Michael <xvorpxvobby@gmail.com>
License: MIT
Project-URL: Homepage, https://github.com/Mk3Ang8l/GuardianLayer
Project-URL: Repository, https://github.com/Mk3Ang8l/GuardianLayer
Project-URL: Documentation, https://github.com/Mk3Ang8l/GuardianLayer
Project-URL: Issue Tracker, https://github.com/Mk3Ang8l/GuardianLayer/issues
Project-URL: Changelog, https://github.com/Mk3Ang8l/GuardianLayer/blob/main/CHANGELOG.md
Project-URL: Funding (PayPal), https://www.paypal.com/paypalme/MicaPaul138
Keywords: ai,agent,loop-detection,circuit-breaker,meta-cognition,llm,langchain,autogen,mcp,model-context-protocol,ai-safety,guardrails,observability
Classifier: Development Status :: 5 - Production/Stable
Classifier: Intended Audience :: Developers
Classifier: Intended Audience :: Science/Research
Classifier: Topic :: Software Development :: Libraries :: Python Modules
Classifier: Topic :: Scientific/Engineering :: Artificial Intelligence
Classifier: Topic :: Software Development :: Quality Assurance
Classifier: License :: OSI Approved :: MIT License
Classifier: Programming Language :: Python
Classifier: Programming Language :: Python :: 3
Classifier: Programming Language :: Python :: 3 :: Only
Classifier: Programming Language :: Python :: 3.8
Classifier: Programming Language :: Python :: 3.9
Classifier: Programming Language :: Python :: 3.10
Classifier: Programming Language :: Python :: 3.11
Classifier: Programming Language :: Python :: 3.12
Classifier: Environment :: Console
Classifier: Operating System :: OS Independent
Classifier: Framework :: AsyncIO
Classifier: Framework :: Pydantic
Classifier: Typing :: Typed
Requires-Python: >=3.8
License-File: LICENSE
Requires-Dist: aiosqlite>=0.19.0
Requires-Dist: sqlalchemy>=2.0.0
Provides-Extra: dev
Requires-Dist: pytest>=7.0.0; extra == "dev"
Requires-Dist: pytest-asyncio>=0.21.0; extra == "dev"
Requires-Dist: pytest-cov>=4.0.0; extra == "dev"
Requires-Dist: ruff>=0.1.0; extra == "dev"
Requires-Dist: mypy>=1.0.0; extra == "dev"
Requires-Dist: black>=23.0.0; extra == "dev"
Requires-Dist: pre-commit>=2.20.0; extra == "dev"
Provides-Extra: docs
Requires-Dist: sphinx>=5.0.0; extra == "docs"
Requires-Dist: sphinx-rtd-theme>=1.2.0; extra == "docs"
Requires-Dist: sphinx-autodoc-typehints>=1.23.0; extra == "docs"
Requires-Dist: myst-parser>=1.0.0; extra == "docs"
Provides-Extra: postgres
Requires-Dist: asyncpg>=0.28.0; extra == "postgres"
Provides-Extra: redis
Requires-Dist: redis>=4.5.0; extra == "redis"
Provides-Extra: all
Requires-Dist: GuardianLayer[postgres]; extra == "all"
Requires-Dist: GuardianLayer[redis]; extra == "all"
Dynamic: license-file
